nimbit/__init__.py
nimbit/agent.py
nimbit/agent_utils/agent_system_prompt.py
nimbit/agentfile.py
nimbit/cli.py
nimbit/examples/basic.py
nimbit/llm/__init__.py
nimbit/llm/base_model_provider.py
nimbit/llm/ollama_provider.py
nimbit/mesh/__init__.py
nimbit/mesh/default_agent_runtime.py
nimbit/mesh/message.py
nimbit/mesh/pulsar_admin.py
nimbit/mesh/pulsar_client.py
nimbit/mesh/schema.py
nimbit/utils/prompts.py
nimbit-0.0.1.dist-info/METADATA
nimbit-0.0.1.dist-info/WHEEL
nimbit-0.0.1.dist-info/entry_points.txt
nimbit-0.0.1.dist-info/RECORD
